Metadata-Version: 1.1
Name: requests-facebook-py3
Version: 0.2.1
Summary: A Python Library to interface with Facebook Graph API
Home-page: https://github.com/michaelhelmick/requests-facebook/
Author: Mike Helmick
Author-email: me@michaelhelmick.com
License: BSD
Download-URL: https://github.com/michaelhelmick/requests-facebook/zipball/master
Keywords: python facebook requests graph oauth oauth2 api
Platform: UNKNOWN
Classifier: Development Status :: 4 - Beta
Classifier: Intended Audience :: Developers
Classifier: License :: OSI Approved :: MIT License
Classifier: Topic :: Software Development :: Libraries :: Python Modules
Classifier: Topic :: Communications :: Chat
Classifier: Topic :: Internet
